abakus_checks/__init__.py
abakus_checks/cli.py
abakus_checks/register.py
abakus_checks/checks/__init__.py
abakus_checks/checks/cpu.py
abakus_checks/checks/load.py
abakus_checks/utils/__init__.py
abakus_checks/utils/check.py
abakus_checks/utils/exit_hook.py
abakus_status_checks-0.0.1.dist-info/DESCRIPTION.rst
abakus_status_checks-0.0.1.dist-info/METADATA
abakus_status_checks-0.0.1.dist-info/RECORD
abakus_status_checks-0.0.1.dist-info/WHEEL
abakus_status_checks-0.0.1.dist-info/entry_points.txt
abakus_status_checks-0.0.1.dist-info/metadata.json
abakus_status_checks-0.0.1.dist-info/top_level.txt
tests/__init__.py
tests/test_case.py
tests/test_cpu_check.py
tests/test_load_check.py
