Metadata-Version: 2.0
Name: abakus-status-checks
Version: 0.0.1
Summary: Abakus Status Checks
Home-page: git@github.com:eirsyl/abakus-status-checks.git
Author: Eirik Martiniussen Sylliaas
Author-email: eirik@sylliaas.no
License: MIT
Keywords: Monitoring,Status Checks,Abakus
Platform: UNKNOWN
Classifier: Intended Audience :: Developers
Classifier: License :: OSI Approved :: MIT License
Classifier: Natural Language :: English
Classifier: Programming Language :: Python :: 2
Classifier: Programming Language :: Python :: 2.7
Classifier: Programming Language :: Python :: 3
Classifier: Programming Language :: Python :: 3.5
Requires-Dist: click (==6.2)
Requires-Dist: psutil (>dev)
Requires-Dist: requests[security] (==2.8.1)
Requires-Dist: six
Requires-Dist: wheel
